[
  {
    "filename": "data.js",
    "code": "import BaseGroup from './group';\r\nimport BaseNode from './node';\r\nimport BaseEdge from './edge';\r\nimport BaseEndpoint from './endpoint';\r\n\r\nexport default {\r\n  nodes: [{\r\n    id: '0',\r\n    top: 160,\r\n    left: 40,\r\n    width: 80,\r\n    height: 80,\r\n    border: 'solid',\r\n    text: 'ATOMIC',\r\n    Class: BaseNode,\r\n    endpoints: [{\r\n      id: 'right',\r\n      orientation: [1, 0],\r\n      pos: [0, 0.5],\r\n      Class: BaseEndpoint\r\n    }]\r\n  }, {\r\n    id: '1',\r\n    top: 200,\r\n    left: 120,\r\n    width: 80,\r\n    height: 80,\r\n    group: 'group_1',\r\n    border: 'dashed',\r\n    text: 'ATOMIC',\r\n    Class: BaseNode,\r\n    endpoints: [{\r\n      id: 'left',\r\n      orientation: [-1, 0],\r\n      pos: [0, 0.5],\r\n      Class: BaseEndpoint\r\n    }, {\r\n      id: 'right_1',\r\n      orientation: [1, 0],\r\n      pos: [0, 0.33],\r\n      Class: BaseEndpoint\r\n    }, {\r\n      id: 'right_2',\r\n      orientation: [1, 0],\r\n      pos: [0, 0.66],\r\n      Class: BaseEndpoint\r\n    }]\r\n  }, {\r\n    id: '2',\r\n    top: 50,\r\n    left: 650,\r\n    width: 100,\r\n    height: 300,\r\n    border: 'solid',\r\n    text: 'ATOMIC',\r\n    Class: BaseNode,\r\n    endpoints: [{\r\n      id: 'left_1',\r\n      orientation: [-1, 0],\r\n      pos: [0, 0.33],\r\n      Class: BaseEndpoint\r\n    }, {\r\n      id: 'left_2',\r\n      orientation: [-1, 0],\r\n      pos: [0, 0.66],\r\n      Class: BaseEndpoint\r\n    }]\r\n  }],\r\n  groups: [{\r\n    id: 'group_1',\r\n    top: 50,\r\n    left: 220,\r\n    text: 'COUPLED',\r\n    Class: BaseGroup,\r\n    endpoints: [{\r\n      id: 'left',\r\n      orientation: [-1, 0],\r\n      pos: [0, 0.5],\r\n      Class: BaseEndpoint\r\n    }, {\r\n      id: 'right_1',\r\n      orientation: [1, 0],\r\n      pos: [0, 0.33],\r\n      Class: BaseEndpoint\r\n    }, {\r\n      id: 'right_2',\r\n      orientation: [1, 0],\r\n      pos: [0, 0.66],\r\n      Class: BaseEndpoint\r\n    }]\r\n  }],\r\n  edges: [{\r\n    source: 'right',\r\n    target: 'left',\r\n    sourceNode: '0',\r\n    targetNode: 'group_1',\r\n    type: 'endpoint',\r\n    label: ['IN', 'OUT'],\r\n    Class: BaseEdge\r\n  }, {\r\n    source: 'left',\r\n    target: 'left',\r\n    sourceNode: 'group_1',\r\n    targetNode: '1',\r\n    type: 'endpoint',\r\n    label: [undefined, 'XY'],\r\n    Class: BaseEdge\r\n  }, {\r\n    source: 'right_1',\r\n    target: 'right_1',\r\n    sourceNode: '1',\r\n    targetNode: 'group_1',\r\n    type: 'endpoint',\r\n    label: ['X', 'OUT1'],\r\n    Class: BaseEdge\r\n  }, {\r\n    source: 'right_2',\r\n    target: 'right_2',\r\n    sourceNode: '1',\r\n    targetNode: 'group_1',\r\n    type: 'endpoint',\r\n    label: ['Y', 'OUT2'],\r\n    Class: BaseEdge\r\n  }, {\r\n    source: 'right_1',\r\n    target: 'left_1',\r\n    sourceNode: 'group_1',\r\n    targetNode: '2',\r\n    type: 'endpoint',\r\n    label: [undefined, 'A'],\r\n    Class: BaseEdge\r\n  }, {\r\n    source: 'right_2',\r\n    target: 'left_2',\r\n    sourceNode: 'group_1',\r\n    targetNode: '2',\r\n    type: 'endpoint',\r\n    label: [undefined, 'B'],\r\n    Class: BaseEdge\r\n  }]\r\n};\r\n"
  },
  {
    "filename": "edge.js",
    "code": "import {Edge} from 'butterfly-dag';\r\nimport $ from 'jquery';\r\n\r\nclass BaseEdge extends Edge {\r\n  draw(obj) {\r\n    let path = super.draw(obj);\r\n    $(path).addClass('base-link');\r\n    return path;\r\n  }\r\n  // 随时定制label的位置和样式\r\n  redrawLabel() {\r\n    if (this._labelDom0) {\r\n      let beginPoint = this.dom.getPointAtLength(0);\r\n      $(this._labelDom0)\r\n        .css('left', beginPoint.x - this._labelDom0.offsetWidth / 2 + 20)\r\n        .css('top', beginPoint.y - this._labelDom0.offsetHeight / 2 + 20);\r\n    }\r\n    if (this._labelDom1) {\r\n      let pathLength = this.dom.getTotalLength();\r\n      let endPoint = this.dom.getPointAtLength(pathLength);\r\n      $(this._labelDom1)\r\n        .css('left', endPoint.x - this._labelDom1.offsetWidth / 2 - 20)\r\n        .css('top', endPoint.y - this._labelDom1.offsetHeight / 2 + 20);\r\n    }\r\n  }\r\n  drawLabel(texts) {\r\n    let dom = null;\r\n    if (texts) {\r\n      dom = document.createDocumentFragment();\r\n      let inText = texts[0];\r\n      let outText = texts[1];\r\n      if (inText) {\r\n        let dom0 = $(`<span class=\"in-label label\">${inText}</span>`)[0];\r\n        dom.append(dom0);\r\n        this._labelDom0 = dom0;\r\n      }\r\n      if (outText) {\r\n        let dom1 = $(`<span class=\"out-label label\">${outText}</span>`)[0];\r\n        dom.append(dom1);\r\n        this._labelDom1 = dom1;\r\n      }\r\n    }\r\n    return dom;\r\n  }\r\n}\r\n\r\nexport default BaseEdge;\r\n"
  },
  {
    "filename": "endpoint.js",
    "code": "import {Endpoint, Tips} from 'butterfly-dag';\r\nimport $ from 'jquery';\r\n\r\nclass BaseEndpoint extends Endpoint {\r\n  mounted() {\r\n    Tips.createTip({\r\n      targetDom: this.dom,\r\n      genTipDom: (data) => {\r\n        return $('<div>this is a tips</div>')[0];\r\n      },\r\n      placement: 'top'\r\n    });\r\n  }\r\n  draw(obj) {\r\n    let point = super.draw(obj);\r\n    $(point).addClass('purple-point');\r\n    return point;\r\n  }\r\n}\r\n\r\nexport default BaseEndpoint;\r\n"
  },
  {
    "filename": "group.js",
    "code": "import {Group} from 'butterfly-dag';\r\nimport $ from 'jquery';\r\nimport _ from 'lodash';\r\n\r\nclass BaseGroup extends Group {\r\n  draw(obj) {\r\n    let _dom = obj.dom;\r\n    if (!_dom) {\r\n      _dom = $('<div></div>')\r\n        .attr('class', 'group')\r\n        .css('top', obj.top)\r\n        .css('left', obj.left)\r\n        .attr('id', obj.id);\r\n    }\r\n    let group = $(_dom);\r\n\r\n    this._container = $('<div></div>')\r\n      .attr('class', 'container');\r\n\r\n    group.append(this._container);\r\n\r\n    // 添加文字\r\n    if (_.get(obj, 'options.text')) {\r\n      group.append(`<span class=\"text\">${obj.options.text}</span>`);\r\n    }\r\n\r\n    return _dom;\r\n  }\r\n}\r\n\r\nexport default BaseGroup;\r\n"
  },
  {
    "filename": "index.jsx",
    "code": "import React, {Component} from 'react';\r\nimport ReactDOM from 'react-dom';\r\nimport {Canvas} from 'butterfly-dag';\r\nimport mockData from './data';\r\nimport './index.less';\r\nimport 'butterfly-dag/dist/index.css';\r\n\r\nclass System extends Component {\r\n  constructor() {\r\n    super();\r\n  }\r\n  componentDidMount() {\r\n    let root = document.getElementById('dag-canvas');\r\n    this.canvas = new Canvas({\r\n      root: root,\r\n      disLinkable: true, // 可删除连线\r\n      linkable: true,    // 可连线\r\n      draggable: true,   // 可拖动\r\n      zoomable: true,    // 可放大\r\n      moveable: true,    // 可平移\r\n      theme: {\r\n        edge: {\r\n          shapeType: 'Straight'\r\n        }\r\n      }\r\n    });\r\n    this.canvas.draw(mockData);\r\n  }\r\n  render() {\r\n    return (\r\n      <div className='system-page'>\r\n        <div className=\"system-canvas\" id=\"dag-canvas\">\r\n        </div>\r\n      </div>\r\n    );\r\n  }\r\n}\r\n\r\nReactDOM.render(<System />, document.getElementById('root'));\r\n\r\n"
  },
  {
    "filename": "index.less",
    "code": "@import 'theme.less'; \n.system-page {\r\n  width: 100%;\r\n  height: 100%;\r\n  .system-canvas {\r\n    width: 100%;\r\n    height: 100%;\r\n    .group {\r\n      width: 300px;\r\n      height: 300px;\r\n      .container {\r\n        width: 100%;\r\n        height: 100%;\r\n        border-radius: 5px;\r\n        border: 1px solid #66cdc5;\r\n        background: @butterfly-theme-color;\r\n      }\r\n    }\r\n    .system-base-node {\r\n      position: absolute;\r\n      padding: 0;\r\n      border-width: 1px;\r\n      border-color: #f4b871;\r\n      text-align: center;\r\n      background: @butterfly-theme-color;\r\n      vertical-align: middle;\r\n      border-radius: 5px;\r\n    }\r\n    .base-link {\r\n      stroke: #4b4f6b;\r\n      stroke-width: 1px;\r\n    }\r\n    .group {\r\n      > .text {\r\n        position: absolute;\r\n        top: 20px;\r\n        left: 108px;\r\n        width: 100px;\r\n      }\r\n    }\r\n    .label {\r\n      position: absolute;\r\n      color: @butterfly-normal-font-color;\r\n      font-size: 12px;\r\n    }\r\n    .label:hover {\r\n      background: @butterfly-primary-color;\r\n      color: @butterfly-overlay-font-color;\r\n    }\r\n    .text {\r\n      display: inline-block;\r\n      text-align: center;\r\n      color: @butterfly-normal-font-color;\r\n      width: 100%;\r\n      padding-top: 5px;\r\n    }\r\n    .dashed {\r\n      border-style: dashed;\r\n    }\r\n    .solid {\r\n      border-style: solid;\r\n    }\r\n    .purple-point {\r\n      border: 1px solid #fff;\r\n      background: #776ef3;\r\n      width: 10px;\r\n      height: 10px;\r\n    }\r\n  }\r\n}"
  },
  {
    "filename": "node.js",
    "code": "import {Node, Tips} from 'butterfly-dag';\r\nimport $ from 'jquery';\r\n\r\nclass BaseNode extends Node {\r\n  constructor(opts) {\r\n    super(opts);\r\n  }\r\n  mounted() {\r\n    Tips.createMenu({\r\n      targetDom: this.dom,\r\n      genTipDom: (data) => {\r\n        return $('<div>this is a menu</div>')[0];\r\n      },\r\n      placement: 'right',\r\n      closable: true\r\n    });\r\n  }\r\n  draw = (data) => {\r\n    let container = $('<div class=\"system-base-node\"></div>')\r\n      .css('top', data.top)\r\n      .css('left', data.left)\r\n      .css('width', data.options.width)\r\n      .css('height', data.options.height)\r\n      .attr('id', data.id);\r\n\r\n    // 添加外框\r\n    if (data.options.border) {\r\n      container.addClass(data.options.border);\r\n    }\r\n    // 添加文字\r\n    container.append(`<span class=\"text\">${data.options.text}</span>`);\r\n\r\n    return container[0];\r\n  }\r\n}\r\n\r\nexport default BaseNode;\r\n"
  },
  {
    "filename": "package.json",
    "code": "{\r\n  \"name\": \"system\",\r\n  \"cn_name\": \"系统数据流图\",\r\n  \"description\": \"a dag to show system data flow\",\r\n  \"cn_description\": \"用于描述系统数据流的DAG图\",\r\n  \"dependencies\": {\r\n    \"butterfly-dag\": \"*\",\r\n    \"react\": \"^16.0.0\",\r\n    \"react-dom\": \"^16.0.0\",\r\n    \"jquery\": \"*\",\r\n    \"lodash\": \"*\"\r\n  }\r\n}"
  },
  {
    "filename": "theme.less",
    "code": "@butterfly-theme-color-base:#fff;\r\n@butterfly-normal-font-color-base:#222;;\r\n@butterfly-overlay-font-color-base:#FFF;\r\n@butterfly-primary-color-base:#F66902;\r\n@butterfly-box-border-color-base: #D9D9D9;\r\n@butterfly-box-shadow-base:0 2px 3px 0 rgba(0,112,204,0.06);\r\n@butterfly-box-radius-base:100px;\r\n@butterfly-line-color-base: #BFBFBF;\r\n// 主题背景色（画布背景色）\r\n@butterfly-theme-background-color: @butterfly-theme-color-base;\r\n// （各图形框）普通情况背景色\r\n@butterfly-theme-color: fade(@butterfly-theme-color-base,80%);\r\n// 主题色\r\n@butterfly-primary-color: @butterfly-primary-color-base;\r\n// 普通情况下字体颜色\r\n@butterfly-normal-font-color: @butterfly-normal-font-color-base;\r\n// 主题背景色上的字体颜色及icon颜色\r\n@butterfly-overlay-font-color: @butterfly-overlay-font-color-base;\r\n// 拖动时的背景色\r\n@butterfly-box-move-background-color: fade(@butterfly-primary-color, 20%);\r\n// 边框的样式\r\n@butterfly-box-border: 1px solid @butterfly-box-border-color-base;\r\n@butterfly-box-shadow: @butterfly-box-shadow-base;\r\n@butterfly-box-radius: @butterfly-box-radius-base;\r\n@butterfly-box-node-border-hover: 1px solid @butterfly-primary-color;\r\n// 线条样式\r\n@butterfly-line-color: @butterfly-line-color-base;"
  }
]